Metadata-Version: 1.0
Name: RFIDSender
Version: 0.1.12
Summary: Bostin Technology RFID Sender Module
Home-page: http://www.BostinTechnology.com
Author: Matthew Bennett
Author-email: matthew.bennett@bostintechnology.com
License: UNKNOWN
Platform: UNKNOWN
